{"info":[{"course":6,"semestr":1,"speciality_1":"8.204","speciality_2":null,"hours":30,"hours_fact":30,"hours_prev":0,"hours_now":30,"hours_next":0,"hours_auditorial":10,"lectures":6,"laboratory":null,"practice":4,"self_work":20,"corse_work":"","rgr":null,"exam":"","credit":"З","control_work":null,"kafedra":"1.4.","record_num":0,"form_of_study":"0","duration":"0","code":202884281},{"course":6,"semestr":1,"speciality_1":"8.204","speciality_2":null,"hours":60,"hours_fact":60,"hours_prev":0,"hours_now":60,"hours_next":0,"hours_auditorial":20,"lectures":10,"laboratory":null,"practice":10,"self_work":40,"corse_work":"","rgr":null,"exam":"Е","credit":"","control_work":null,"kafedra":"4.3.","record_num":1,"form_of_study":"0","duration":"0","code":202884638},{"course":6,"semestr":1,"speciality_1":"8.204","speciality_2":null,"hours":90,"hours_fact":90,"hours_prev":0,"hours_now":90,"hours_next":0,"hours_auditorial":30,"lectures":16,"laboratory":null,"practice":14,"self_work":60,"corse_work":"","rgr":null,"exam":"Е","credit":"","control_work":null,"kafedra":"4.3.","record_num":2,"form_of_study":"0","duration":"0","code":202884622},{"course":6,"semestr":1,"speciality_1":"8.204","speciality_2":null,"hours":105,"hours_fact":105,"hours_prev":0,"hours_now":105,"hours_next":0,"hours_auditorial":36,"lectures":12,"laboratory":null,"practice":24,"self_work":69,"corse_work":"","rgr":null,"exam":"Е","credit":"","control_work":null,"kafedra":"4.3.","record_num":3,"form_of_study":"0","duration":"0","code":202884634},{"course":6,"semestr":1,"speciality_1":"8.204","speciality_2":null,"hours":135,"hours_fact":135,"hours_prev":0,"hours_now":135,"hours_next":0,"hours_auditorial":46,"lectures":16,"laboratory":null,"practice":30,"self_work":89,"corse_work":"","rgr":null,"exam":"Е","credit":"","control_work":null,"kafedra":"4.1.","record_num":4,"form_of_study":"0","duration":"0","code":202884576},{"course":6,"semestr":1,"speciality_1":"8.204","speciality_2":null,"hours":525,"hours_fact":180,"hours_prev":0,"hours_now":180,"hours_next":345,"hours_auditorial":60,"lectures":30,"laboratory":null,"practice":30,"self_work":120,"corse_work":"","rgr":null,"exam":"","credit":"З","control_work":null,"kafedra":"4.3.","record_num":5,"form_of_study":"0","duration":"0","code":202884620},{"course":6,"semestr":1,"speciality_1":"8.204","speciality_2":null,"hours":45,"hours_fact":45,"hours_prev":0,"hours_now":45,"hours_next":0,"hours_auditorial":16,"lectures":null,"laboratory":null,"practice":16,"self_work":29,"corse_work":"","rgr":null,"exam":"","credit":"З","control_work":null,"kafedra":"6.1.2.","record_num":6,"form_of_study":"0","duration":"0","code":202884725},{"course":6,"semestr":1,"speciality_1":"8.204","speciality_2":null,"hours":60,"hours_fact":60,"hours_prev":0,"hours_now":60,"hours_next":0,"hours_auditorial":20,"lectures":10,"laboratory":null,"practice":10,"self_work":40,"corse_work":"","rgr":null,"exam":"","credit":"З","control_work":null,"kafedra":"4.1.","record_num":7,"form_of_study":"0","duration":"0","code":202884598},{"course":6,"semestr":2,"speciality_1":"8.204","speciality_2":null,"hours":525,"hours_fact":525,"hours_prev":180,"hours_now":345,"hours_next":0,"hours_auditorial":116,"lectures":60,"laboratory":null,"practice":56,"self_work":229,"corse_work":"КПф","rgr":null,"exam":"Е","credit":"","control_work":null,"kafedra":"4.3.","record_num":8,"form_of_study":"0","duration":"0","code":202884620},{"course":6,"semestr":2,"speciality_1":"8.204","speciality_2":null,"hours":60,"hours_fact":60,"hours_prev":0,"hours_now":60,"hours_next":0,"hours_auditorial":20,"lectures":10,"laboratory":null,"practice":10,"self_work":40,"corse_work":"","rgr":null,"exam":"Е","credit":"","control_work":null,"kafedra":"7.3.","record_num":9,"form_of_study":"0","duration":"0","code":202884899},{"course":6,"semestr":2,"speciality_1":"8.204","speciality_2":null,"hours":60,"hours_fact":60,"hours_prev":0,"hours_now":60,"hours_next":0,"hours_auditorial":20,"lectures":10,"laboratory":null,"practice":10,"self_work":40,"corse_work":"","rgr":null,"exam":"Е","credit":"","control_work":null,"kafedra":"4.3.","record_num":10,"form_of_study":"0","duration":"0","code":202884641},{"course":6,"semestr":2,"speciality_1":"8.204","speciality_2":null,"hours":60,"hours_fact":60,"hours_prev":0,"hours_now":60,"hours_next":0,"hours_auditorial":20,"lectures":10,"laboratory":null,"practice":10,"self_work":40,"corse_work":"","rgr":null,"exam":"","credit":"З","control_work":null,"kafedra":"6.1.2.","record_num":11,"form_of_study":"0","duration":"0","code":202884737},{"course":6,"semestr":2,"speciality_1":"8.204","speciality_2":null,"hours":45,"hours_fact":45,"hours_prev":0,"hours_now":45,"hours_next":0,"hours_auditorial":null,"lectures":null,"laboratory":null,"practice":null,"self_work":45,"corse_work":"","rgr":null,"exam":"","credit":"ДЗ","control_work":null,"kafedra":"4.3.","record_num":12,"form_of_study":"0","duration":"0","code":202884163},{"course":6,"semestr":2,"speciality_1":"8.204","speciality_2":null,"hours":150,"hours_fact":150,"hours_prev":0,"hours_now":150,"hours_next":0,"hours_auditorial":50,"lectures":30,"laboratory":null,"practice":20,"self_work":100,"corse_work":"","rgr":null,"exam":"","credit":"З","control_work":null,"kafedra":"4.2.","record_num":13,"form_of_study":"0","duration":"0","code":202884604},{"course":6,"semestr":2,"speciality_1":"8.204","speciality_2":null,"hours":270,"hours_fact":270,"hours_prev":0,"hours_now":270,"hours_next":0,"hours_auditorial":90,"lectures":60,"laboratory":null,"practice":30,"self_work":180,"corse_work":"","rgr":null,"exam":"Е","credit":"","control_work":null,"kafedra":"4.3.","record_num":14,"form_of_study":"0","duration":"0","code":202884621}]}